.gitignore
CHANGES.txt
CONTRIBUTORS.txt
COPYRIGHT.txt
LICENSE.txt
README.txt
TODO.txt
setup.cfg
setup.py
tox.ini
docs/Makefile
docs/conf.py
docs/index.rst
docs/_static/exclaim.png
docs/_static/exclaim_color.png
docs/_static/info.png
docs/_static/info_color.png
docs/_static/onebit_36.png
docs/_static/onebit_38.png
docs/_static/pyramid.png
docs/_static/pyramid_epub.css
pyramid_who/__init__.py
pyramid_who/classifiers.py
pyramid_who/meta.zcml
pyramid_who/whov2.py
pyramid_who/zcml.py
pyramid_who.egg-info/PKG-INFO
pyramid_who.egg-info/SOURCES.txt
pyramid_who.egg-info/dependency_links.txt
pyramid_who.egg-info/entry_points.txt
pyramid_who.egg-info/not-zip-safe
pyramid_who.egg-info/requires.txt
pyramid_who.egg-info/top_level.txt
pyramid_who/tests/__init__.py
pyramid_who/tests/test_classifiers.py
pyramid_who/tests/test_whov2.py
pyramid_who/tests/test_zcml.py