Metadata-Version: 1.0
Name: pyramid-who
Version: 0.3
Summary: Pyramid authentication policies based on repoze.who
Home-page: http://docs.pylonshq.com
Author: Tres Seaver, Agendaless Consulting
Author-email: pylons-discuss@googlegroups.com
License: BSD-derived (http://www.repoze.org/LICENSE.txt)
Keywords: web wsgi pyramid pylons repoze who authentication
Platform: UNKNOWN
Classifier: Intended Audience :: Developers
Classifier: Programming Language :: Python
Classifier: Framework :: Pylons
